pystare/__init__.py
pystare/_core.cpython-312-x86_64-linux-gnu.so
pystare/_version.py
pystare/exceptions.py
pystare/spatial.py
pystare/temporal.py
pystare-0.8.14.dist-info/METADATA
pystare-0.8.14.dist-info/WHEEL
pystare-0.8.14.dist-info/top_level.txt
pystare-0.8.14.dist-info/RECORD
