Metadata-Version: 2.2
Name: pystare
Version: 0.8.14
Summary: PySTARE exposes the STARE library to python.
Home-page: https://github.com/SpatioTemporal/pystare
Author: NiklasGriessbaum
Author-email: griessbaum@ucsb.edu
Project-URL: Bug Tracker, https://github.com/SpatioTemporal/pystare/issues
Classifier: Programming Language :: Python :: 3
Classifier: License :: OSI Approved :: MIT License
Classifier: Operating System :: OS Independent
Requires-Python: >=3.12
Requires-Dist: numpy>=2.2.1
Provides-Extra: test
Requires-Dist: numpy; extra == "test"
Requires-Dist: matplotlib; extra == "test"
Requires-Dist: pytest; extra == "test"
Requires-Dist: pytest-cov; extra == "test"
Requires-Dist: astropy; extra == "test"
Provides-Extra: docs
Requires-Dist: sphinx; extra == "docs"
Requires-Dist: numpydoc; extra == "docs"
